hich/__init__.py
hich/__main__.py
hich/commands/fasta.py
hich/commands/matrix.py
hich/commands/pairs.py
hich/commands/workflow.py
hich/fasta/__init__.py
hich/fasta/digest_re.py
hich/matrix/hicrep.py
hich/pairs/__init__.py
hich/pairs/convert.py
hich/pairs/header.py
hich/pairs/map_ends.py
hich/pairs/pairssql.py
hich-0.2.8.dist-info/entry_points.txt
hich-0.2.8.dist-info/WHEEL
hich-0.2.8.dist-info/METADATA
hich-0.2.8.dist-info/RECORD
